td_connect/__init__.py
td_connect/cli.py
td_connect/td_connect.py
td_connect-0.2.3.dist-info/entry_points.txt
td_connect-0.2.3.dist-info/WHEEL
td_connect-0.2.3.dist-info/METADATA
td_connect-0.2.3.dist-info/RECORD
