Metadata-Version: 2.1
Name: td-connect
Version: 0.2.3
Summary: Authentication utilities for TD Ameritrade REST APIs.
Author: Dan Kelleher
Author-email: kelleherjdan@gmail.com
Requires-Python: >=3.8,<4.0
Classifier: Programming Language :: Python :: 3
Classifier: Programming Language :: Python :: 3.10
Classifier: Programming Language :: Python :: 3.8
Classifier: Programming Language :: Python :: 3.9
Requires-Dist: SQLAlchemy (>=1.4.36,<2.0.0)
Requires-Dist: aiohttp (>=3.8.1,<4.0.0)
Requires-Dist: alert-msgs (>=0.1.1,<0.2.0)
Requires-Dist: click (>=8.1.3,<9.0.0)
Requires-Dist: psycopg2 (>=2.9.3,<3.0.0)
Requires-Dist: python-dateutil (>=2.8.2,<3.0.0)
Requires-Dist: ready-logger (>=0.1.0,<0.2.0)
Requires-Dist: requests (>=2.26.0,<3.0.0)
Requires-Dist: websockets (>=10.1,<11.0)
